{
  "vpc-provider:account=782110148236:filter.vpc-id=vpc-c80dd1b1:region=eu-west-1:returnAsymmetricSubnets=true": {
    "vpcId": "vpc-c80dd1b1",
    "vpcCidrBlock": "172.31.0.0/16",
    "ownerAccountId": "782110148236",
    "availabilityZones": [],
    "subnetGroups": [
      {
        "name": "Public",
        "type": "Public",
        "subnets": [
          {
            "subnetId": "subnet-86bca5ce",
            "cidr": "172.31.16.0/20",
            "availabilityZone": "eu-west-1a",
            "routeTableId": "rtb-bd9c5ac5"
          },
          {
            "subnetId": "subnet-66d3983c",
            "cidr": "172.31.32.0/20",
            "availabilityZone": "eu-west-1b",
            "routeTableId": "rtb-bd9c5ac5"
          },
          {
            "subnetId": "subnet-e1747d87",
            "cidr": "172.31.0.0/20",
            "availabilityZone": "eu-west-1c",
            "routeTableId": "rtb-bd9c5ac5"
          }
        ]
      },
      {
        "name": "Private",
        "type": "Private",
        "subnets": [
          {
            "subnetId": "subnet-05ab827f9a556a73c",
            "cidr": "172.31.48.0/20",
            "availabilityZone": "eu-west-1a",
            "routeTableId": "rtb-032fdee6a70df2382"
          }
        ]
      }
    ]
  }
}
